[{"id":"4e9c437a-b26b-46d3-bb70-1aad2d3e191e","category":"Hypotheek","monthly_limit":899.58,"created_at":"2026-06-16T23:17:58.029118+00:00"}, 
 {"id":"83fa9814-f347-4983-aa7c-ccf643e5a3ad","category":"Internet","monthly_limit":51.55,"created_at":"2026-06-16T23:17:59.687615+00:00"}, 
 {"id":"250ec1c1-3987-4ec7-bf67-da87a94d5407","category":"Verzekeringen","monthly_limit":47.48,"created_at":"2026-06-16T23:18:00.601029+00:00"}, 
 {"id":"5db6f791-2063-405d-9a64-38440005e8da","category":"Boodschappen","monthly_limit":280.00,"created_at":"2026-06-16T23:18:09.227729+00:00"}]